xindy/__init__.py
xindy/__main__.py
xindy/cli.py
xindy/_modules/README
xindy/_modules/class/pagenums.xdy
xindy/_modules/lang/german/din5007.xdy
xindy/_modules/lang/german/din5007m.xdy
xindy/_modules/lang/german/duden.xdy
xindy/_modules/lang/german/rules.xdy
xindy/_modules/lang/german/tex.xdy
xindy/_modules/lang/latin/caseisrt.xdy
xindy/_modules/lang/latin/letgroup.xdy
xindy/_modules/ord/letorder.xdy
xindy/_modules/rules/isolatin1-exchange.xdy
xindy/_modules/rules/isolatin1-tolower.xdy
xindy/_modules/rules/latin-exchange.xdy
xindy/_modules/rules/latin-tolower.xdy
xindy/_modules/tex/README
xindy/_modules/tex/isolatin1m-tex.xdy
xindy/_modules/tex/isolatin1m.xdy
xindy/_modules/tex/isolatin1s-tex.xdy
xindy/_modules/tex/isolatin1s.xdy
xindy/_modules/tex/isolatin2m-tex.xdy
xindy/_modules/tex/isolatin2m.xdy
xindy/_modules/tex/isolatin2s-tex.xdy
xindy/_modules/tex/isolatin2s.xdy
xindy/_modules/tex/isolatinm.xdy
xindy/_modules/tex/isolatins.xdy
xindy/_modules/tex/makeidx.xdy
xindy/_modules/tex/makeidx4.xdy
xindy/dsl/__init__.py
xindy/dsl/interpreter.py
xindy/dsl/sexpr.py
xindy/index/__init__.py
xindy/index/builder.py
xindy/index/grouping.py
xindy/index/hierarchy.py
xindy/index/models.py
xindy/index/order.py
xindy/locref/__init__.py
xindy/locref/basetypes.py
xindy/locref/classes.py
xindy/locref/references.py
xindy/markup/__init__.py
xindy/markup/renderer.py
xindy/raw/__init__.py
xindy/raw/reader.py
xindy/tex/__init__.py
xindy/tex/makeglossaries.py
xindy/tex/makeindex4.py
xindy/tex/tex2xindy.py
pyxindy-0.0.6.dist-info/METADATA
pyxindy-0.0.6.dist-info/WHEEL
pyxindy-0.0.6.dist-info/entry_points.txt
pyxindy-0.0.6.dist-info/licenses/LICENSE
pyxindy-0.0.6.dist-info/RECORD
