Metadata-Version: 2.4
Name: pyxindy
Version: 0.0.6
Summary: Python port of the xindy (flexible index) processor.
License-File: LICENSE
Requires-Python: >=3.10
Requires-Dist: click>=8.1
